soso/__init__.py
soso/data/mime.types
soso/data/soso_common_v1.2.3.ttl
soso/interface.py
soso/main.py
soso/strategies/__init__.py
soso/strategies/eml/__init__.py
soso/strategies/eml/eml.py
soso/strategies/eml/eml.xml
soso/strategies/eml/eml_empty.xml
soso/strategies/eml/soso-eml.sssom.tsv
soso/strategies/eml/soso-eml.sssom.yml
soso/strategies/spase/__init__.py
soso/strategies/spase/conversion.py
soso/strategies/spase/soso-spase.sssom.tsv
soso/strategies/spase/soso-spase.sssom.yml
soso/strategies/spase/spase-ignoreCreatorSplit.txt
soso/strategies/spase/spase.py
soso/strategies/spase/spase.xml
soso/strategies/spase/spase_empty.xml
soso/utilities.py
soso/validation.py
soso-0.7.1.dist-info/METADATA
soso-0.7.1.dist-info/WHEEL
soso-0.7.1.dist-info/licenses/LICENSE
soso-0.7.1.dist-info/RECORD
