Metadata-Version: 2.4
Name: soso
Version: 0.7.1
Summary: For Converting Metadata Records into Science On Schema.Org Markup
License: MIT
License-File: LICENSE
Author: Colin Smith
Author-email: colin.smith@wisc.edu
Maintainer: Colin Smith
Maintainer-email: colin.smith@wisc.edu
Requires-Python: >=3.11,<4.0
Classifier: License :: OSI Approved :: MIT License
Classifier: Programming Language :: Python :: 3
Classifier: Programming Language :: Python :: 3.11
Classifier: Programming Language :: Python :: 3.12
Classifier: Programming Language :: Python :: 3.13
Classifier: Programming Language :: Python :: 3.14
Requires-Dist: daiquiri (>=3.0.0,<4.0.0)
Requires-Dist: lxml (>=5.0.0,<6.0.0)
Requires-Dist: pyshacl (>=0.26.0,<0.27.0)
Requires-Dist: requests (>=2.32.0,<3.0.0)
